[{"id":"jkatDxQBBCDIeZNS","title":"1","createdAt":"2023-04-17T08:39:44.892Z","photos":["/api/photos/BkLHgXKZkGZEMljm.jpeg","/api/photos/egnkmhzAmQDDOVkw.jpeg","/api/photos/BHQdRrKIJEwJfCoX.jpeg"]},{"id":"OmpRKxWcIxBIAMxt","title":"2","createdAt":"2023-04-17T13:29:49.235Z","photos":["/api/photos/DikctNaCbjOyzAiw.jpeg","/api/photos/UXDQCTVjtTgxGkLR.jpeg","/api/photos/lRIPlMqeeouxDDlz.jpeg","/api/photos/YllPLWcqOAGiFcsc.jpeg","/api/photos/OhYIOdPJNJvvxAOg.jpeg","/api/photos/DzUcKnmvJgKUpOLq.jpeg"]},{"id":"wLBowadDnIetjlNf","title":"3","createdAt":"2023-04-17T13:29:49.829Z","photos":["/api/photos/IuHnyJrItjxOXhnI.jpeg","/api/photos/McyIchZawSjlDToT.jpeg"]}]