{
	"info": {
		"_postman_id": "e9818803-caa3-494a-bbb1-15a919e685ed",
		"name": "CMPS 350 - Lab 08",
		"schema": "https://schema.getpostman.com/json/collection/v2.1.0/collection.json",
		"_exporter_id": "8340285"
	},
	"item": [
		{
			"name": "/api/accounts?type",
			"request": {
				"method": "GET",
				"header": [],
				"url": {
					"raw": "http://localhost:3000/api/accounts?type=current",
					"protocol": "http",
					"host": [
						"localhost"
					],
					"port": "3000",
					"path": [
						"api",
						"accounts"
					],
					"query": [
						{
							"key": "type",
							"value": "current"
						}
					]
				}
			},
			"response": []
		},
		{
			"name": "/api/accounts",
			"request": {
				"method": "POST",
				"header": [],
				"body": {
					"mode": "raw",
					"raw": "{\n    \"balance\": 500,\n    \"type\": \"current\"\n}",
					"options": {
						"raw": {
							"language": "json"
						}
					}
				},
				"url": {
					"raw": "http://localhost:3000/api/accounts",
					"protocol": "http",
					"host": [
						"localhost"
					],
					"port": "3000",
					"path": [
						"api",
						"accounts"
					],
					"query": [
						{
							"key": "",
							"value": null,
							"disabled": true
						}
					]
				}
			},
			"response": []
		},
		{
			"name": "/api/accounts/:id",
			"request": {
				"method": "GET",
				"header": [],
				"url": {
					"raw": "http://localhost:3000/api/accounts/:id",
					"protocol": "http",
					"host": [
						"localhost"
					],
					"port": "3000",
					"path": [
						"api",
						"accounts",
						":id"
					],
					"variable": [
						{
							"key": "id",
							"value": "BAlAksK9MjUZ9PDVjdune"
						}
					]
				}
			},
			"response": []
		},
		{
			"name": "/api/accounts/:id",
			"request": {
				"method": "PUT",
				"header": [],
				"body": {
					"mode": "raw",
					"raw": "{\n    \"balance\": 50000\n}",
					"options": {
						"raw": {
							"language": "json"
						}
					}
				},
				"url": {
					"raw": "http://localhost:3000/api/accounts/:id",
					"protocol": "http",
					"host": [
						"localhost"
					],
					"port": "3000",
					"path": [
						"api",
						"accounts",
						":id"
					],
					"variable": [
						{
							"key": "id",
							"value": "BAlAksK9MjUZ9PDVjdune"
						}
					]
				}
			},
			"response": []
		},
		{
			"name": "/api/accounts/:id",
			"request": {
				"method": "DELETE",
				"header": [],
				"url": {
					"raw": "http://localhost:3000/api/accounts/:id",
					"protocol": "http",
					"host": [
						"localhost"
					],
					"port": "3000",
					"path": [
						"api",
						"accounts",
						":id"
					],
					"variable": [
						{
							"key": "id",
							"value": "BAlAksK9MjUZ9PDVjdune"
						}
					]
				}
			},
			"response": []
		},
		{
			"name": "/api/accounts/:id/transactions",
			"request": {
				"method": "GET",
				"header": [],
				"url": {
					"raw": "http://localhost:3000/api/accounts/:id/transactions",
					"protocol": "http",
					"host": [
						"localhost"
					],
					"port": "3000",
					"path": [
						"api",
						"accounts",
						":id",
						"transactions"
					],
					"variable": [
						{
							"key": "id",
							"value": "g6M7vwbsYPeBlDHhWLQyE"
						}
					]
				}
			},
			"response": []
		},
		{
			"name": "/api/accounts/:id/transactions",
			"request": {
				"method": "POST",
				"header": [],
				"body": {
					"mode": "raw",
					"raw": "{\n    \"type\": \"w\",\n    \"amount\": 1000\n}",
					"options": {
						"raw": {
							"language": "json"
						}
					}
				},
				"url": {
					"raw": "http://localhost:3000/api/accounts/:id/transactions",
					"protocol": "http",
					"host": [
						"localhost"
					],
					"port": "3000",
					"path": [
						"api",
						"accounts",
						":id",
						"transactions"
					],
					"variable": [
						{
							"key": "id",
							"value": "g6M7vwbsYPeBlDHhWLQyE"
						}
					]
				}
			},
			"response": []
		}
	]
}